get_cov2/__init__.py
get_cov2/main.py
get_cov2-0.0.7.dist-info/LICENSE
get_cov2-0.0.7.dist-info/METADATA
get_cov2-0.0.7.dist-info/WHEEL
get_cov2-0.0.7.dist-info/top_level.txt
get_cov2-0.0.7.dist-info/RECORD
