Metadata-Version: 2.1
Name: get-cov2
Version: 0.0.7
Summary: Calculation of co-effecient of variance for series
Home-page: https://github.com/arjunjanamatti/get_cov2
Author: Arjun Janamatti
Author-email: arjunjanamatti@gmail.com
Classifier: Programming Language :: Python :: 3
Classifier: License :: OSI Approved :: MIT License
Classifier: Operating System :: OS Independent
Requires-Python: >=3.7
License-File: LICENSE
